twiner/__init__.py
twiner/cli.py
twiner/config.py
twiner/notify.py
twiner/twitch.py
twiner-0.4.1.dist-info/LICENSE
twiner-0.4.1.dist-info/METADATA
twiner-0.4.1.dist-info/WHEEL
twiner-0.4.1.dist-info/entry_points.txt
twiner-0.4.1.dist-info/RECORD
