Metadata-Version: 2.1
Name: twiner
Version: 0.4.1
Summary: CLI that helps you with notifications for your favorite streamers on Twitch.tv.
Author: febits
Author-email: febits@proton.me
Requires-Python: >=3.11,<4.0
Classifier: Development Status :: 5 - Production/Stable
Classifier: Environment :: Console
Classifier: License :: OSI Approved :: MIT License
Classifier: Operating System :: POSIX :: Linux
Classifier: Programming Language :: Python :: 3
Classifier: Programming Language :: Python :: 3.11
Classifier: Programming Language :: Python :: 3.12
Requires-Dist: dbus-python (>=1.3.2,<2.0.0)
Requires-Dist: plyer (>=2.1.0,<3.0.0)
Requires-Dist: python-dotenv (>=1.0.1,<2.0.0)
Requires-Dist: pyyaml (>=6.0.1,<7.0.0)
Requires-Dist: requests (>=2.31.0,<3.0.0)
Requires-Dist: rich (>=13.7.0,<14.0.0)
Requires-Dist: typer[all] (>=0.9.0,<0.10.0)
Requires-Dist: wget (>=3.2,<4.0)
Project-URL: Homepage, https://pypi.org/project/twiner
Project-URL: Source, https://github.com/febits/twiner
